watchmen_storage_postgresql/__init__.py
watchmen_storage_postgresql/data_source_postgresql.py
watchmen_storage_postgresql/script_builder_postgresql.py
watchmen_storage_postgresql/storage_postgresql.py
watchmen_storage_postgresql/storage_postgresql_configuration.py
watchmen_storage_postgresql/table_creator.py
watchmen_storage_postgresql/where_build.py
watchmen_storage_postgresql-18.0.1.dist-info/METADATA
watchmen_storage_postgresql-18.0.1.dist-info/WHEEL
watchmen_storage_postgresql-18.0.1.dist-info/licenses/LICENSE
watchmen_storage_postgresql-18.0.1.dist-info/RECORD
